CHANGES.txt
MANIFEST.in
README.rst
setup.py
django_shell_ipynb/__init__.py
django_shell_ipynb.egg-info/PKG-INFO
django_shell_ipynb.egg-info/SOURCES.txt
django_shell_ipynb.egg-info/dependency_links.txt
django_shell_ipynb.egg-info/requires.txt
django_shell_ipynb.egg-info/top_level.txt
django_shell_ipynb/management/__init__.py
django_shell_ipynb/management/commands/__init__.py
django_shell_ipynb/management/commands/shell_ipynb.py