Metadata-Version: 1.1
Name: django-shell-ipynb
Version: 0.3.0
Summary: A Django management command "shell_ipynb" that uses the ipython notebook instead of ipython.
Home-page: https://github.com/cpbotha/django-shell-ipynb
Author: Charl P. Botha
Author-email: cpbotha@vxlabs.com
License: BSD
Keywords: django ipython notebook shell
Platform: UNKNOWN
Classifier: Development Status :: 4 - Beta
Classifier: Environment :: Web Environment
Classifier: Framework :: Django
Classifier: Intended Audience :: Developers
Classifier: License :: OSI Approved :: BSD License
Classifier: Operating System :: OS Independent
Classifier: Programming Language :: Python
Classifier: Topic :: Software Development :: Libraries :: Python Modules
